[
  {
    "id" : 1,
    "ru" : "Абстракция",
    "en": "Abstraction",
    "url": "abstraction"
  },
  {
    "id" : 2,
    "ru" : "Автомобили",
    "en": "Cars",
    "url": "cars"
  },
  {
    "id" : 3,
    "ru" : "Аниме",
    "en": "Anime",
    "url": "anime"
  },
  {
    "id" : 4,
    "ru" : "Видеоигры",
    "en": "Video games",
    "url": "games"
  },
  {
    "id" : 5,
    "ru" : "Визуализация",
    "en": "Visualization",
    "url": "visualization"
  },
  {
    "id" : 6,
    "ru" : "Девушки",
    "en": "Girls",
    "url": "girls"
  },
  {
    "id" : 7,
    "ru" : "Животные",
    "en": "Animals",
    "url": "animals"
  },
  {
    "id" : 8,
    "ru" : "Космос",
    "en": "Space",
    "url": "space"
  },
  {
    "id" : 9,
    "ru" : "Люди",
    "en": "People",
    "url": "people"
  },
  {
    "id" : 10,
    "ru" : "Моря",
    "en": "The seas",
    "url": "s"
  },
  {
    "id" : 11,
    "ru" : "Природа",
    "en": "Nature",
    "url": "nature"
  },
  {
    "id" : 12,
    "ru" : "Самолеты",
    "en": "Aircraft",
    "url": "aircraft"
  },
  {
    "id" : 13,
    "ru" : "Фантастика",
    "en": "Fantasy",
    "url": "fantasy"
  }
]